unredoable/__init__.py
unredoable/_unredoable.py
unredoable-0.0.5.dist-info/LICENSE
unredoable-0.0.5.dist-info/WHEEL
unredoable-0.0.5.dist-info/METADATA
unredoable-0.0.5.dist-info/RECORD
