Metadata-Version: 2.1
Name: unredoable
Version: 0.0.5
Summary: Object-specific undoing and redoing functionality through wrapper class
Home-page: https://github.com/w2sv/monostate
License: MIT
Keywords: state-management,frontend,web-development,gui,undoing,redoing
Author: w2sv
Author-email: zangenbergjanek@googlemail.com
Requires-Python: >=3.6,<4.0
Classifier: License :: OSI Approved :: MIT License
Classifier: Operating System :: OS Independent
Classifier: Programming Language :: Python :: 3
Classifier: Programming Language :: Python :: 3.10
Classifier: Programming Language :: Python :: 3.6
Classifier: Programming Language :: Python :: 3.7
Classifier: Programming Language :: Python :: 3.8
Classifier: Programming Language :: Python :: 3.9
Project-URL: Repository, https://github.com/w2sv/monostate
